[
  {
    "weights" : [
      0.35,
      0.05,
      0.4,
      0.83,
      0.98,
      0.69,
      0.37,
      0.96,
      0.37,
      0.79,
      0.86,
      0.35,
      1.0,
      0.04,
      0.52,
      0.55,
      0.25,
      0.25,
      0.4,
      0.35,
      0.54,
      15.48
    ],
    "avgActions" : 55,
    "avgRemainingHealth" : 59.91,
    "avgRemainingEnergy" : 74.1,
    "avgGoalCompletion" : 27.28,
    "fitness" : 0.35
  },
  {
    "weights" : [
      0.09,
      0.05,
      0.05,
      0.83,
      0.96,
      0.69,
      0.37,
      0.8,
      0.0,
      0.6,
      0.83,
      0.97,
      0.58,
      0.78,
      0.11,
      0.55,
      0.51,
      0.0,
      0.13,
      0.98,
      0.54,
      25.96
    ],
    "avgActions" : 54,
    "avgRemainingHealth" : 59.9,
    "avgRemainingEnergy" : 67.12,
    "avgGoalCompletion" : 25.35,
    "fitness" : 0.33
  },
  {
    "weights" : [
      0.0,
      0.05,
      0.78,
      0.83,
      0.98,
      0.69,
      0.37,
      0.96,
      0.71,
      0.79,
      0.76,
      0.98,
      0.66,
      1.0,
      0.28,
      0.55,
      0.25,
      0.19,
      0.29,
      1.0,
      0.54,
      17.84
    ],
    "avgActions" : 52,
    "avgRemainingHealth" : 74.0,
    "avgRemainingEnergy" : 37.8,
    "avgGoalCompletion" : 0.0,
    "fitness" : 0.14
  },
  {
    "weights" : [
      0.0,
      0.05,
      0.12,
      0.83,
      0.98,
      0.39,
      0.37,
      1.0,
      0.37,
      0.79,
      0.86,
      0.55,
      0.58,
      0.57,
      0.11,
      0.94,
      0.25,
      0.23,
      0.45,
      0.98,
      0.54,
      17.84
    ],
    "avgActions" : 49,
    "avgRemainingHealth" : 61.89,
    "avgRemainingEnergy" : 43.08,
    "avgGoalCompletion" : 0.85,
    "fitness" : 0.15
  },
  {
    "weights" : [
      0.09,
      0.02,
      0.29,
      0.51,
      0.98,
      0.42,
      0.37,
      0.96,
      0.37,
      0.79,
      0.86,
      0.97,
      0.58,
      0.91,
      0.0,
      0.37,
      0.25,
      0.38,
      0.62,
      0.98,
      0.54,
      5.58
    ],
    "avgActions" : 44,
    "avgRemainingHealth" : 59.89,
    "avgRemainingEnergy" : 47.62,
    "avgGoalCompletion" : 0.0,
    "fitness" : 0.15
  },
  {
    "weights" : [
      0.09,
      0.05,
      0.37,
      0.83,
      0.92,
      0.29,
      0.37,
      0.96,
      0.37,
      0.79,
      0.86,
      0.97,
      0.82,
      0.7,
      0.11,
      1.0,
      0.25,
      0.38,
      0.4,
      0.57,
      0.54,
      17.84
    ],
    "avgActions" : 29,
    "avgRemainingHealth" : 21.49,
    "avgRemainingEnergy" : 61.98,
    "avgGoalCompletion" : 1.06,
    "fitness" : 0.15
  },
  {
    "weights" : [
      0.09,
      0.0,
      0.74,
      0.83,
      0.98,
      0.69,
      0.37,
      0.51,
      0.37,
      0.79,
      0.86,
      1.0,
      0.58,
      1.0,
      0.11,
      0.55,
      0.25,
      0.38,
      0.4,
      0.98,
      0.67,
      17.84
    ],
    "avgActions" : 49,
    "avgRemainingHealth" : 68.0,
    "avgRemainingEnergy" : 42.4,
    "avgGoalCompletion" : 0.0,
    "fitness" : 0.15
  },
  {
    "weights" : [
      0.09,
      0.05,
      0.29,
      0.83,
      0.98,
      0.69,
      0.37,
      0.96,
      0.37,
      0.79,
      0.86,
      0.97,
      0.58,
      1.0,
      0.11,
      0.55,
      0.25,
      0.38,
      0.4,
      0.98,
      0.54,
      17.84
    ],
    "avgActions" : 45,
    "avgRemainingHealth" : 61.89,
    "avgRemainingEnergy" : 45.76,
    "avgGoalCompletion" : 0.0,
    "fitness" : 0.15
  },
  {
    "weights" : [
      0.09,
      0.05,
      0.29,
      0.83,
      0.98,
      0.69,
      0.37,
      0.96,
      0.37,
      0.79,
      0.86,
      0.97,
      0.58,
      1.0,
      0.11,
      0.55,
      0.25,
      0.38,
      0.4,
      0.98,
      0.54,
      17.84
    ],
    "avgActions" : 45,
    "avgRemainingHealth" : 61.89,
    "avgRemainingEnergy" : 45.76,
    "avgGoalCompletion" : 0.0,
    "fitness" : 0.15
  },
  {
    "weights" : [
      0.09,
      0.05,
      0.29,
      0.83,
      0.98,
      0.69,
      0.37,
      0.96,
      0.37,
      0.79,
      0.86,
      0.97,
      0.58,
      1.0,
      0.11,
      0.55,
      0.25,
      0.38,
      0.4,
      0.98,
      0.54,
      17.84
    ],
    "avgActions" : 45,
    "avgRemainingHealth" : 61.89,
    "avgRemainingEnergy" : 45.76,
    "avgGoalCompletion" : 0.0,
    "fitness" : 0.15
  }
]